django_achilles-0.0.13.dist-info/METADATA
django_achilles-0.0.13.dist-info/WHEEL
django_achilles-0.0.13.dist-info/DESCRIPTION.rst
django_achilles-0.0.13.dist-info/RECORD
django_achilles-0.0.13.dist-info/top_level.txt
django_achilles-0.0.13.dist-info/metadata.json
achilles/common.py
achilles/__init__.py
achilles/views.py
achilles/messages.py
achilles/redirect.py
achilles/urls.py
achilles/actions.py
achilles/console.py
achilles/forms.py
achilles/models.py
achilles/blocks.py
achilles/static/js/achilles.js
achilles/static/js/jquery.min.js
achilles/static/js/achilles-cov.js
achilles/templatetags/__init__.py
achilles/templatetags/achilles.py
achilles/tables/common.py
achilles/tables/__init__.py
achilles/tables/columns.py
achilles/templates/achilles/form.html
achilles/templates/achilles/table.html
