Metadata-Version: 2.0
Name: django-achilles
Version: 0.0.13
Summary: Django AJAX Framework
Home-page: http://github.com/exekias/django-achilles/
Author: Carlos Pérez-Aradros Herce
Author-email: exekias@gmail.com
License: Apache License (2.0)
Platform: UNKNOWN
Classifier: Development Status :: 3 - Alpha
Classifier: Environment :: Web Environment
Classifier: Operating System :: OS Independent
Classifier: License :: OSI Approved :: Apache Software License
Classifier: Programming Language :: Python
Classifier: Framework :: Django
Classifier: Intended Audience :: Developers
Classifier: Topic :: Internet :: WWW/HTTP :: Dynamic Content
Requires-Dist: Django (>=1.4)
Requires-Dist: six
